LICENSE
README.md
setup.py
example_module_andan/__init__.py
example_module_andan/paint.py
example_module_andan.egg-info/PKG-INFO
example_module_andan.egg-info/SOURCES.txt
example_module_andan.egg-info/dependency_links.txt
example_module_andan.egg-info/requires.txt
example_module_andan.egg-info/top_level.txt